framler/__init__.py
framler/_base.py
framler/articles.py
framler/cleaners.py
framler/cli.py
framler/config.yaml
framler/configs.py
framler/exporters.py
framler/extractors.py
framler/html.yaml
framler/images.py
framler/log.py
framler/parsers.py
framler/temp.py
framler/utils.py
framler-0.1.1.dist-info/AUTHORS.rst
framler-0.1.1.dist-info/LICENSE
framler-0.1.1.dist-info/METADATA
framler-0.1.1.dist-info/WHEEL
framler-0.1.1.dist-info/top_level.txt
framler-0.1.1.dist-info/RECORD
