Metadata-Version: 2.1
Name: framler
Version: 0.1.1
Summary: Python package for crawler data and extract main information 
Home-page: https://github.com/huyhoang17/framler
Author: Phan Hoang
Author-email: phan.huy.hoang@framgia.com 
License: MIT license
Keywords: framler
Platform: UNKNOWN
Classifier: Development Status :: 2 - Pre-Alpha
Classifier: Intended Audience :: Developers
Classifier: License :: OSI Approved :: MIT License
Classifier: Natural Language :: English
Classifier: Programming Language :: Python :: 2
Classifier: Programming Language :: Python :: 2.7
Classifier: Programming Language :: Python :: 3
Classifier: Programming Language :: Python :: 3.4
Classifier: Programming Language :: Python :: 3.5
Classifier: Programming Language :: Python :: 3.6
Classifier: Programming Language :: Python :: 3.7
Requires-Dist: beautifulsoup4 (==4.7.1)
Requires-Dist: certifi (==2018.11.29)
Requires-Dist: chardet (==3.0.4)
Requires-Dist: Click (==7.0)
Requires-Dist: datefinder (==0.7.0)
Requires-Dist: idna (==2.8)
Requires-Dist: lxml (==4.3.2)
Requires-Dist: python-dateutil (==2.8.0)
Requires-Dist: pytz (==2018.9)
Requires-Dist: PyYAML (==3.13)
Requires-Dist: regex (==2019.3.12)
Requires-Dist: requests (==2.21.0)
Requires-Dist: selenium (==3.141.0)
Requires-Dist: six (==1.12.0)
Requires-Dist: soupsieve (==1.8)
Requires-Dist: tqdm (==4.31.1)
Requires-Dist: urllib3 (==1.24.1)
